b2handle/__init__.py
b2handle/clientcredentials.py
b2handle/compatibility_helper.py
b2handle/handleclient.py
b2handle/handleclientinherited.py
b2handle/handleclientoriginal.py
b2handle/handleclientpyhandle.py
b2handle/handleexceptions.py
b2handle/handlesystemconnector.py
b2handle/hsresponses.py
b2handle/searcher.py
b2handle/utilhandle.py
b2handle/tests/__init__.py
b2handle/tests/main_test_script.py
b2handle/tests/mockresponses.py
b2handle/tests/utilities.py
b2handle/tests/resources/handlerecord_for_reading_PUBLIC.json
b2handle/tests/resources/handlerecord_with_10320LOC_PUBLIC.json
b2handle/tests/resources/handlerecord_with_empty_10320LOC_PUBLIC.json
b2handle/tests/resources/handlerecord_without_10320LOC_PUBLIC.json
b2handle/tests/resources/testvalues_for_clientcredentials_tests_PUBLIC.json
b2handle/tests/resources/testvalues_for_integration_tests_template_PUBLIC.json
b2handle/tests/testcases/__init__.py
b2handle/tests/testcases/clientcredentials_unit_test.py
b2handle/tests/testcases/handleclient_10320loc_read_patched_unit_test.py
b2handle/tests/testcases/handleclient_10320loc_write_integration_test.py
b2handle/tests/testcases/handleclient_2_read_patched_unit_test.py
b2handle/tests/testcases/handleclient_read_integration_test.py
b2handle/tests/testcases/handleclient_read_patched_unit_test.py
b2handle/tests/testcases/handleclient_search_integration_test.py
b2handle/tests/testcases/handleclient_search_unit_test.py
b2handle/tests/testcases/handleclient_unit_test.py
b2handle/tests/testcases/handleclient_write_integration_test.py
b2handle/tests/testcases/handleclient_write_patched_unit_test.py
b2handle/tests/testcases/handleconnector_patched_unit_test.py
b2handle/tests/testcases/handleconnector_unit_test.py
b2handle/tests/testcases/utilconfig_unit_test.py
b2handle/tests/testcredentials/credentials_brokensyntax_PUBLIC.json
b2handle/tests/testcredentials/credentials_correct_PUBLIC.json
b2handle/tests/testcredentials/credentials_correct_with_cert_PUBLIC.json
b2handle-1.1.2.dist-info/LICENSE
b2handle-1.1.2.dist-info/METADATA
b2handle-1.1.2.dist-info/NOTICE
b2handle-1.1.2.dist-info/WHEEL
b2handle-1.1.2.dist-info/top_level.txt
b2handle-1.1.2.dist-info/RECORD
