Metadata-Version: 2.1
Name: b2handle
Version: 1.1.2
Summary: Library for management of handles in the EUDAT project.
Home-page: http://eudat-b2safe.github.io/B2HANDLE
Author: EUDAT project, subtask 5.3.3
Author-email: buurman@dkrz.de
License: Apache License 2.0
Download-URL: https://github.com/EUDAT-B2SAFE/B2HANDLE
Keywords: handles,PIDs
Platform: UNKNOWN
Classifier: Development Status :: 5 - Production/Stable
Classifier: Programming Language :: Python :: 2
Classifier: Programming Language :: Python :: 2.6
Classifier: Programming Language :: Python :: 2.7
Classifier: Programming Language :: Python :: 3
Classifier: Programming Language :: Python :: 3.5
Classifier: Programming Language :: Python :: 3.6
Classifier: Programming Language :: Python :: 3.7
Classifier: License :: OSI Approved :: Apache Software License
Classifier: Intended Audience :: Developers
Classifier: Topic :: Software Development :: Libraries :: Python Modules
Requires-Python: >=2.6,!=3.0.*,!=3.1.*,!=3.2.*,!=3.3.*,!=3.4.*,<3.8
Requires-Dist: requests
Requires-Dist: datetime
Requires-Dist: future
Requires-Dist: six
